carterpcs/__init__.py
carterpcs/carterpcs.py
carterpcs-6.7.4.1.dist-info/METADATA
carterpcs-6.7.4.1.dist-info/WHEEL
carterpcs-6.7.4.1.dist-info/top_level.txt
carterpcs-6.7.4.1.dist-info/RECORD
