Metadata-Version: 2.4
Name: carterpcs
Version: 6.7.4.1
Summary: j
Author: dom!
Classifier: Programming Language :: Python :: 3
Classifier: Operating System :: OS Independent
Requires-Python: >=3.9
